Metadata-Version: 2.1
Name: hoy-typed-input
Version: 1.1
Summary: Pequena biblioteca para obrigar o usuário a digitar um tipo de dado específico
Author: Alan Reis Anjos
Author-email: alanreisanjo@gmail.com
License: MIT License
Keywords: Hoy Typed Input
License-File: LICENSE
